Complex_Number_Encryptor/ComplexNumber.py
Complex_Number_Encryptor/__init__.py
Complex_Number_Encryptor_Janderion-1.0.0.dist-info/LICENSE
Complex_Number_Encryptor_Janderion-1.0.0.dist-info/METADATA
Complex_Number_Encryptor_Janderion-1.0.0.dist-info/WHEEL
Complex_Number_Encryptor_Janderion-1.0.0.dist-info/top_level.txt
Complex_Number_Encryptor_Janderion-1.0.0.dist-info/RECORD
