Metadata-Version: 2.1
Name: Complex-Number-Encryptor-Janderion
Version: 1.0.0
Summary: Package that can encrypt messages using various math equations
Home-page: https://github.com/Janderion47/Complex-Number-Encryptor
Author: Jadenpaul M. Albay
Author-email: Janderion369@gmail.com
License: UNKNOWN
Platform: UNKNOWN
Classifier: Programming Language :: Python :: 3
Classifier: License :: OSI Approved :: GNU General Public License v3 (GPLv3)
Classifier: Operating System :: OS Independent
Requires-Python: >=3.7
